{
  "character_number": 35,
  "name": "No name",
  "musics": [
    "resources/sounds/ragtime_1_MA_BrunoFreitas_OldWestSaloon_HonkyTonk.ogg"
  ],
  "ambiance": "resources/sounds/ambiance_saloon.ogg",
  "paths": [
    {
      "gametypes": [
        "basic",
        "advanced"
      ],
      "points": [
        [
          388,
          207
        ],
        [
          362,
          192
        ],
        [
          360,
          169
        ],
        [
          344,
          126
        ],
        [
          314,
          107
        ],
        [
          280,
          109
        ],
        [
          258,
          121
        ],
        [
          245,
          147
        ],
        [
          244,
          179
        ],
        [
          245,
          206
        ],
        [
          229,
          227
        ],
        [
          213,
          234
        ],
        [
          190,
          236
        ],
        [
          177,
          237
        ]
      ],
      "hard": false
    },
    {
      "gametypes": [
        "basic",
        "advanced"
      ],
      "points": [
        [
          194,
          224
        ],
        [
          177,
          255
        ],
        [
          178,
          270
        ],
        [
          196,
          282
        ],
        [
          215,
          298
        ],
        [
          237,
          301
        ],
        [
          248,
          286
        ],
        [
          246,
          259
        ],
        [
          255,
          233
        ],
        [
          275,
          216
        ],
        [
          301,
          213
        ],
        [
          330,
          224
        ],
        [
          345,
          245
        ],
        [
          347,
          267
        ],
        [
          344,
          290
        ],
        [
          366,
          307
        ],
        [
          380,
          308
        ]
      ],
      "hard": false
    },
    {
      "gametypes": [
        "basic",
        "advanced"
      ],
      "points": [
        [
          379,
          229
        ],
        [
          398,
          223
        ],
        [
          432,
          225
        ],
        [
          465,
          220
        ],
        [
          491,
          203
        ],
        [
          496,
          179
        ],
        [
          497,
          151
        ],
        [
          483,
          121
        ],
        [
          464,
          110
        ],
        [
          437,
          108
        ],
        [
          407,
          109
        ],
        [
          390,
          122
        ],
        [
          377,
          135
        ],
        [
          372,
          149
        ],
        [
          369,
          169
        ]
      ],
      "hard": false
    },
    {
      "gametypes": [
        "basic",
        "advanced"
      ],
      "points": [
        [
          364,
          205
        ],
        [
          397,
          217
        ],
        [
          450,
          211
        ],
        [
          462,
          201
        ],
        [
          471,
          180
        ],
        [
          474,
          152
        ],
        [
          456,
          127
        ],
        [
          438,
          121
        ],
        [
          407,
          121
        ],
        [
          377,
          131
        ],
        [
          359,
          155
        ],
        [
          347,
          185
        ],
        [
          326,
          200
        ],
        [
          313,
          201
        ],
        [
          282,
          201
        ],
        [
          267,
          193
        ],
        [
          252,
          181
        ],
        [
          242,
          163
        ],
        [
          242,
          140
        ],
        [
          253,
          124
        ],
        [
          265,
          105
        ],
        [
          286,
          101
        ],
        [
          310,
          102
        ]
      ],
      "hard": false
    },
    {
      "gametypes": [
        "basic",
        "advanced"
      ],
      "points": [
        [
          342,
          138
        ],
        [
          349,
          200
        ],
        [
          337,
          229
        ],
        [
          368,
          278
        ],
        [
          411,
          309
        ],
        [
          467,
          304
        ],
        [
          508,
          267
        ],
        [
          477,
          225
        ]
      ],
      "hard": false
    },
    {
      "gametypes": [
        "basic",
        "advanced"
      ],
      "points": [
        [
          492,
          199
        ],
        [
          432,
          222
        ],
        [
          371,
          191
        ],
        [
          358,
          144
        ],
        [
          385,
          114
        ],
        [
          459,
          108
        ],
        [
          502,
          97
        ]
      ],
      "hard": false
    },
    {
      "gametypes": [
        "basic",
        "advanced"
      ],
      "points": [
        [
          476,
          98
        ],
        [
          503,
          105
        ],
        [
          514,
          133
        ],
        [
          491,
          153
        ],
        [
          508,
          178
        ],
        [
          518,
          208
        ],
        [
          508,
          244
        ],
        [
          477,
          242
        ],
        [
          466,
          215
        ],
        [
          440,
          225
        ],
        [
          396,
          200
        ],
        [
          340,
          211
        ]
      ],
      "hard": false
    },
    {
      "gametypes": [
        "basic",
        "advanced"
      ],
      "points": [
        [
          300,
          206
        ],
        [
          248,
          217
        ],
        [
          238,
          244
        ],
        [
          247,
          274
        ],
        [
          227,
          284
        ],
        [
          190,
          256
        ],
        [
          162,
          257
        ],
        [
          161,
          234
        ],
        [
          216,
          221
        ],
        [
          242,
          181
        ],
        [
          228,
          151
        ],
        [
          231,
          109
        ]
      ],
      "hard": false
    },
    {
      "gametypes": [
        "basic",
        "advanced"
      ],
      "points": [
        [
          252,
          93
        ],
        [
          237,
          121
        ],
        [
          230,
          150
        ],
        [
          240,
          178
        ],
        [
          248,
          200
        ],
        [
          213,
          230
        ],
        [
          183,
          233
        ],
        [
          185,
          260
        ],
        [
          214,
          254
        ],
        [
          215,
          241
        ]
      ],
      "hard": false
    },
    {
      "gametypes": [
        "basic",
        "advanced"
      ],
      "points": [
        [
          368,
          204
        ],
        [
          356,
          229
        ],
        [
          356,
          250
        ],
        [
          352,
          274
        ],
        [
          338,
          291
        ],
        [
          324,
          299
        ],
        [
          294,
          307
        ],
        [
          259,
          305
        ],
        [
          234,
          296
        ],
        [
          236,
          268
        ],
        [
          243,
          237
        ]
      ],
      "hard": false
    },
    {
      "gametypes": [
        "basic",
        "advanced"
      ],
      "points": [
        [
          334,
          217
        ],
        [
          396,
          210
        ],
        [
          436,
          197
        ],
        [
          477,
          195
        ],
        [
          506,
          174
        ],
        [
          515,
          144
        ],
        [
          501,
          114
        ],
        [
          475,
          98
        ],
        [
          438,
          98
        ],
        [
          396,
          109
        ],
        [
          370,
          116
        ],
        [
          339,
          109
        ],
        [
          321,
          103
        ]
      ],
      "hard": false
    },
    {
      "gametypes": [
        "basic",
        "advanced"
      ],
      "points": [
        [
          282,
          99
        ],
        [
          305,
          116
        ],
        [
          342,
          121
        ],
        [
          365,
          139
        ],
        [
          370,
          163
        ],
        [
          383,
          192
        ],
        [
          399,
          206
        ],
        [
          430,
          214
        ],
        [
          477,
          237
        ],
        [
          489,
          260
        ],
        [
          487,
          278
        ],
        [
          473,
          291
        ]
      ],
      "hard": false
    },
    {
      "gametypes": [
        "basic",
        "advanced"
      ],
      "points": [
        [
          458,
          302
        ],
        [
          411,
          308
        ],
        [
          384,
          295
        ],
        [
          362,
          271
        ],
        [
          358,
          246
        ],
        [
          371,
          230
        ],
        [
          393,
          221
        ],
        [
          433,
          224
        ],
        [
          462,
          229
        ],
        [
          476,
          226
        ],
        [
          495,
          198
        ],
        [
          501,
          181
        ],
        [
          504,
          159
        ]
      ],
      "hard": false
    },
    {
      "gametypes": [
        "basic",
        "advanced"
      ],
      "points": [
        [
          485,
          182
        ],
        [
          456,
          204
        ],
        [
          435,
          206
        ],
        [
          384,
          204
        ],
        [
          360,
          206
        ]
      ],
      "hard": false
    },
    {
      "gametypes": [
        "basic",
        "advanced"
      ],
      "points": [
        [
          255,
          201
        ],
        [
          305,
          214
        ],
        [
          332,
          233
        ],
        [
          340,
          253
        ],
        [
          346,
          268
        ]
      ],
      "hard": false
    },
    {
      "gametypes": [
        "basic",
        "advanced"
      ],
      "points": [
        [
          337,
          175
        ],
        [
          336,
          209
        ],
        [
          332,
          232
        ],
        [
          335,
          246
        ],
        [
          362,
          280
        ],
        [
          386,
          297
        ],
        [
          411,
          307
        ],
        [
          439,
          308
        ],
        [
          478,
          308
        ],
        [
          494,
          307
        ],
        [
          502,
          304
        ],
        [
          508,
          275
        ],
        [
          508,
          253
        ],
        [
          501,
          225
        ],
        [
          495,
          211
        ],
        [
          498,
          177
        ],
        [
          503,
          153
        ],
        [
          479,
          142
        ],
        [
          465,
          136
        ],
        [
          451,
          121
        ],
        [
          411,
          110
        ],
        [
          376,
          107
        ],
        [
          354,
          109
        ],
        [
          338,
          122
        ],
        [
          321,
          123
        ],
        [
          288,
          123
        ],
        [
          268,
          125
        ],
        [
          257,
          141
        ],
        [
          251,
          156
        ],
        [
          239,
          187
        ],
        [
          228,
          211
        ],
        [
          206,
          225
        ],
        [
          188,
          226
        ],
        [
          172,
          237
        ],
        [
          171,
          253
        ],
        [
          168,
          277
        ],
        [
          171,
          294
        ]
      ],
      "hard": false
    },
    {
      "gametypes": [
        "basic",
        "advanced"
      ],
      "points": [
        [
          158,
          285
        ],
        [
          205,
          312
        ],
        [
          222,
          309
        ],
        [
          227,
          285
        ],
        [
          224,
          258
        ],
        [
          232,
          232
        ],
        [
          259,
          211
        ],
        [
          302,
          216
        ],
        [
          331,
          224
        ],
        [
          341,
          253
        ],
        [
          342,
          281
        ],
        [
          348,
          290
        ]
      ],
      "hard": false
    },
    {
      "gametypes": [
        "basic",
        "advanced"
      ],
      "points": [
        [
          193,
          261
        ],
        [
          228,
          292
        ],
        [
          247,
          301
        ],
        [
          287,
          304
        ],
        [
          339,
          313
        ],
        [
          374,
          309
        ],
        [
          411,
          311
        ],
        [
          454,
          312
        ],
        [
          491,
          303
        ],
        [
          495,
          288
        ],
        [
          504,
          269
        ],
        [
          510,
          244
        ],
        [
          506,
          216
        ]
      ],
      "hard": false
    },
    {
      "gametypes": [
        "basic",
        "advanced"
      ],
      "points": [
        [
          231,
          225
        ],
        [
          279,
          207
        ],
        [
          305,
          209
        ],
        [
          338,
          209
        ],
        [
          349,
          194
        ],
        [
          353,
          174
        ],
        [
          353,
          149
        ],
        [
          325,
          124
        ],
        [
          298,
          111
        ],
        [
          264,
          109
        ],
        [
          250,
          122
        ],
        [
          244,
          136
        ]
      ],
      "hard": false
    },
    {
      "gametypes": [
        "basic",
        "advanced"
      ],
      "points": [
        [
          222,
          91
        ],
        [
          268,
          92
        ],
        [
          311,
          96
        ],
        [
          353,
          103
        ],
        [
          395,
          112
        ],
        [
          456,
          104
        ],
        [
          504,
          96
        ],
        [
          515,
          121
        ],
        [
          515,
          142
        ],
        [
          510,
          170
        ]
      ],
      "hard": false
    },
    {
      "gametypes": [
        "basic",
        "advanced"
      ],
      "points": [
        [
          480,
          125
        ],
        [
          488,
          163
        ],
        [
          482,
          186
        ],
        [
          457,
          204
        ],
        [
          431,
          209
        ],
        [
          402,
          221
        ],
        [
          392,
          229
        ],
        [
          381,
          242
        ],
        [
          373,
          259
        ]
      ],
      "hard": false
    },
    {
      "gametypes": [
        "basic",
        "advanced"
      ],
      "points": [
        [
          358,
          222
        ],
        [
          358,
          262
        ],
        [
          361,
          296
        ],
        [
          344,
          305
        ],
        [
          319,
          311
        ],
        [
          287,
          312
        ],
        [
          255,
          295
        ],
        [
          240,
          276
        ],
        [
          242,
          247
        ],
        [
          259,
          215
        ],
        [
          288,
          211
        ],
        [
          324,
          213
        ],
        [
          352,
          201
        ],
        [
          358,
          182
        ],
        [
          360,
          160
        ],
        [
          366,
          124
        ],
        [
          389,
          110
        ],
        [
          412,
          105
        ],
        [
          437,
          105
        ],
        [
          457,
          113
        ],
        [
          472,
          138
        ]
      ],
      "hard": false
    },
    {
      "gametypes": [
        "basic",
        "advanced"
      ],
      "points": [
        [
          458,
          130
        ],
        [
          476,
          179
        ],
        [
          490,
          224
        ],
        [
          482,
          262
        ],
        [
          453,
          300
        ],
        [
          402,
          308
        ],
        [
          348,
          283
        ],
        [
          340,
          215
        ],
        [
          284,
          198
        ],
        [
          247,
          219
        ],
        [
          199,
          261
        ]
      ],
      "hard": false
    },
    {
      "gametypes": [
        "basic",
        "advanced"
      ],
      "points": [
        [
          250,
          129
        ],
        [
          315,
          101
        ],
        [
          403,
          96
        ],
        [
          476,
          102
        ],
        [
          510,
          130
        ],
        [
          513,
          200
        ]
      ],
      "hard": false
    },
    {
      "gametypes": [
        "basic",
        "advanced"
      ],
      "points": [
        [
          243,
          95
        ],
        [
          339,
          110
        ],
        [
          365,
          149
        ],
        [
          395,
          207
        ],
        [
          466,
          218
        ],
        [
          504,
          261
        ],
        [
          508,
          299
        ]
      ],
      "hard": false
    },
    {
      "gametypes": [
        "basic",
        "advanced"
      ],
      "points": [
        [
          521,
          223
        ],
        [
          448,
          228
        ],
        [
          476,
          264
        ],
        [
          467,
          290
        ],
        [
          403,
          299
        ],
        [
          351,
          284
        ],
        [
          353,
          246
        ],
        [
          443,
          215
        ],
        [
          498,
          166
        ],
        [
          476,
          119
        ]
      ],
      "hard": false
    },
    {
      "gametypes": [
        "basic",
        "advanced"
      ],
      "points": [
        [
          409,
          115
        ],
        [
          380,
          136
        ],
        [
          366,
          175
        ],
        [
          364,
          217
        ]
      ],
      "hard": false
    },
    {
      "gametypes": [
        "basic",
        "advanced"
      ],
      "points": [
        [
          339,
          103
        ],
        [
          358,
          140
        ],
        [
          361,
          199
        ],
        [
          321,
          204
        ],
        [
          277,
          217
        ],
        [
          247,
          240
        ]
      ],
      "hard": false
    },
    {
      "gametypes": [
        "basic",
        "advanced"
      ],
      "points": [
        [
          358,
          229
        ],
        [
          369,
          265
        ],
        [
          388,
          300
        ],
        [
          425,
          309
        ],
        [
          504,
          297
        ],
        [
          528,
          255
        ]
      ],
      "hard": false
    },
    {
      "gametypes": [
        "basic",
        "advanced"
      ],
      "points": [
        [
          363,
          298
        ],
        [
          303,
          313
        ],
        [
          249,
          307
        ],
        [
          227,
          271
        ],
        [
          243,
          220
        ],
        [
          254,
          200
        ],
        [
          231,
          146
        ],
        [
          226,
          109
        ]
      ],
      "hard": false
    },
    {
      "gametypes": [
        "basic",
        "advanced"
      ],
      "points": [
        [
          227,
          177
        ],
        [
          275,
          195
        ],
        [
          337,
          199
        ],
        [
          388,
          212
        ],
        [
          421,
          224
        ],
        [
          478,
          198
        ],
        [
          499,
          156
        ],
        [
          507,
          117
        ]
      ],
      "hard": false
    },
    {
      "gametypes": [
        "basic",
        "advanced"
      ],
      "points": [
        [
          478,
          105
        ],
        [
          406,
          108
        ],
        [
          354,
          105
        ],
        [
          300,
          97
        ]
      ],
      "hard": false
    },
    {
      "gametypes": [
        "basic",
        "advanced"
      ],
      "points": [
        [
          243,
          99
        ],
        [
          332,
          122
        ],
        [
          360,
          131
        ],
        [
          367,
          153
        ]
      ],
      "hard": false
    },
    {
      "gametypes": [
        "basic",
        "advanced"
      ],
      "points": [
        [
          359,
          184
        ],
        [
          357,
          228
        ],
        [
          372,
          273
        ],
        [
          400,
          295
        ],
        [
          436,
          304
        ]
      ],
      "hard": false
    },
    {
      "gametypes": [
        "basic",
        "advanced"
      ],
      "points": [
        [
          485,
          268
        ],
        [
          504,
          211
        ],
        [
          519,
          165
        ],
        [
          522,
          144
        ],
        [
          512,
          99
        ],
        [
          468,
          94
        ],
        [
          447,
          110
        ]
      ],
      "hard": false
    },
    {
      "gametypes": [
        "basic",
        "advanced"
      ],
      "points": [
        [
          404,
          118
        ],
        [
          367,
          121
        ],
        [
          330,
          120
        ],
        [
          300,
          114
        ],
        [
          266,
          114
        ],
        [
          257,
          131
        ],
        [
          239,
          150
        ],
        [
          222,
          177
        ],
        [
          225,
          215
        ],
        [
          201,
          238
        ],
        [
          178,
          243
        ],
        [
          159,
          258
        ],
        [
          162,
          274
        ],
        [
          182,
          286
        ]
      ],
      "hard": false
    },
    {
      "gametypes": [
        "basic",
        "advanced"
      ],
      "points": [
        [
          240,
          231
        ],
        [
          216,
          247
        ],
        [
          206,
          279
        ],
        [
          221,
          292
        ],
        [
          251,
          307
        ],
        [
          327,
          304
        ],
        [
          340,
          280
        ],
        [
          362,
          282
        ],
        [
          378,
          301
        ],
        [
          417,
          309
        ],
        [
          468,
          309
        ],
        [
          507,
          308
        ],
        [
          519,
          293
        ],
        [
          517,
          255
        ],
        [
          515,
          208
        ]
      ],
      "hard": false
    },
    {
      "gametypes": [
        "basic",
        "advanced"
      ],
      "points": [
        [
          153,
          228
        ],
        [
          151,
          276
        ],
        [
          173,
          301
        ],
        [
          211,
          317
        ],
        [
          265,
          308
        ],
        [
          320,
          302
        ],
        [
          349,
          268
        ],
        [
          357,
          240
        ],
        [
          348,
          221
        ]
      ],
      "hard": false
    },
    {
      "gametypes": [
        "basic",
        "advanced"
      ],
      "points": [
        [
          359,
          112
        ],
        [
          358,
          157
        ],
        [
          328,
          192
        ],
        [
          293,
          201
        ],
        [
          263,
          204
        ],
        [
          229,
          211
        ],
        [
          207,
          215
        ]
      ],
      "hard": false
    },
    {
      "gametypes": [
        "basic",
        "advanced"
      ],
      "points": [
        [
          491,
          118
        ],
        [
          508,
          154
        ],
        [
          519,
          195
        ],
        [
          526,
          230
        ],
        [
          504,
          248
        ],
        [
          476,
          224
        ],
        [
          434,
          211
        ]
      ],
      "hard": false
    },
    {
      "gametypes": [
        "basic",
        "advanced"
      ],
      "points": [
        [
          444,
          193
        ],
        [
          395,
          204
        ],
        [
          374,
          212
        ],
        [
          344,
          230
        ],
        [
          358,
          268
        ],
        [
          352,
          289
        ],
        [
          328,
          299
        ],
        [
          271,
          301
        ],
        [
          234,
          272
        ],
        [
          247,
          237
        ],
        [
          297,
          224
        ],
        [
          356,
          203
        ]
      ],
      "hard": false
    },
    {
      "gametypes": [
        "basic",
        "advanced"
      ],
      "points": [
        [
          357,
          113
        ],
        [
          247,
          125
        ],
        [
          238,
          165
        ],
        [
          202,
          228
        ]
      ],
      "hard": false
    }
  ],
  "edit_data": {
    "background_placeholders": [
      {
        "type": "rect",
        "data": [
          0,
          0,
          646,
          362
        ],
        "tile": "woodfloor-vertical.png",
        "color": [
          255,
          255,
          255,
          255
        ]
      },
      {
        "type": "rect",
        "data": [
          139,
          63,
          505,
          19
        ],
        "tile": "wall-green.png",
        "color": [
          255,
          255,
          255,
          255
        ]
      },
      {
        "type": "rect",
        "data": [
          0,
          0,
          645,
          56
        ],
        "tile": "woodfloor-dark-horizontal.png",
        "color": [
          255,
          255,
          255,
          255
        ]
      },
      {
        "type": "rect",
        "data": [
          137,
          32,
          206,
          50
        ],
        "tile": "guardrail_column.png",
        "color": [
          255,
          255,
          255,
          255
        ]
      },
      {
        "type": "rect",
        "data": [
          541,
          0,
          105,
          362
        ],
        "tile": "woodfloor-dark-vertical.png",
        "color": [
          255,
          255,
          255,
          255
        ]
      },
      {
        "type": "rect",
        "data": [
          343,
          53,
          93,
          29
        ],
        "tile": "stair.png",
        "color": [
          255,
          255,
          255,
          255
        ]
      },
      {
        "type": "rect",
        "data": [
          103,
          261,
          1,
          1
        ],
        "tile": null,
        "color": [
          255,
          255,
          255,
          255
        ]
      },
      {
        "type": "rect",
        "data": [
          436,
          32,
          105,
          50
        ],
        "tile": "guardrail_column.png",
        "color": [
          255,
          255,
          255,
          255
        ]
      },
      {
        "type": "rect",
        "data": [
          0,
          337,
          541,
          26
        ],
        "tile": "woodfloor-dark-horizontal.png",
        "color": [
          255,
          255,
          255,
          255
        ]
      },
      {
        "type": "rect",
        "data": [
          0,
          316,
          541,
          21
        ],
        "tile": "gardrail.png",
        "color": [
          255,
          255,
          255,
          255
        ]
      },
      {
        "type": "rect",
        "data": [
          537,
          38,
          4,
          299
        ],
        "tile": null,
        "color": [
          83,
          57,
          23
        ]
      },
      {
        "type": "rect",
        "data": [
          1,
          1,
          136,
          368
        ],
        "tile": "woodfloor-dark-horizontal.png",
        "color": [
          255,
          255,
          255,
          255
        ]
      },
      {
        "type": "rect",
        "data": [
          137,
          39,
          3,
          294
        ],
        "tile": null,
        "color": [
          83,
          57,
          23
        ]
      },
      {
        "type": "rect",
        "data": [
          0,
          -7,
          70,
          385
        ],
        "tile": null,
        "color": [
          25,
          20,
          12
        ]
      },
      {
        "type": "rect",
        "data": [
          140,
          79,
          197,
          3
        ],
        "tile": null,
        "color": [
          100,
          75,
          40
        ]
      },
      {
        "type": "rect",
        "data": [
          442,
          79,
          95,
          3
        ],
        "tile": null,
        "color": [
          100,
          75,
          40
        ]
      },
      {
        "type": "polygon",
        "data": [
          [
            345,
            84
          ],
          [
            342,
            84
          ],
          [
            342,
            86
          ],
          [
            348,
            88
          ],
          [
            352,
            87
          ],
          [
            352,
            84
          ],
          [
            349,
            84
          ],
          [
            349,
            71
          ],
          [
            347,
            71
          ]
        ],
        "tile": null,
        "color": [
          100,
          100,
          100
        ]
      },
      {
        "type": "polygon",
        "data": [
          [
            383,
            84
          ],
          [
            379,
            84
          ],
          [
            380,
            87
          ],
          [
            384,
            88
          ],
          [
            389,
            87
          ],
          [
            391,
            84
          ],
          [
            386,
            84
          ],
          [
            387,
            71
          ],
          [
            384,
            71
          ]
        ],
        "tile": null,
        "color": [
          100,
          100,
          100
        ]
      },
      {
        "type": "polygon",
        "data": [
          [
            424,
            85
          ],
          [
            427,
            84
          ],
          [
            428,
            72
          ],
          [
            431,
            72
          ],
          [
            430,
            84
          ],
          [
            432,
            85
          ],
          [
            432,
            88
          ],
          [
            429,
            89
          ]
        ],
        "tile": null,
        "color": [
          100,
          100,
          100
        ]
      },
      {
        "type": "polygon",
        "data": [
          [
            349,
            72
          ],
          [
            358,
            74
          ],
          [
            368,
            74
          ],
          [
            378,
            74
          ],
          [
            384,
            71
          ],
          [
            384,
            73
          ],
          [
            378,
            76
          ],
          [
            368,
            76
          ],
          [
            358,
            76
          ]
        ],
        "tile": null,
        "color": [
          150,
          125,
          100
        ]
      },
      {
        "type": "polygon",
        "data": [
          [
            387,
            71
          ],
          [
            407,
            74
          ],
          [
            428,
            72
          ],
          [
            428,
            74
          ],
          [
            407,
            76
          ],
          [
            388,
            74
          ]
        ],
        "tile": null,
        "color": [
          150,
          125,
          100
        ]
      },
      {
        "type": "rect",
        "data": [
          302,
          64,
          18,
          13
        ],
        "tile": null,
        "color": [
          100,
          58,
          25
        ]
      },
      {
        "type": "rect",
        "data": [
          310,
          77,
          2,
          8
        ],
        "tile": null,
        "color": [
          100,
          58,
          25
        ]
      },
      {
        "type": "polygon",
        "data": [
          [
            310,
            66
          ],
          [
            306,
            67
          ],
          [
            303,
            71
          ],
          [
            307,
            75
          ],
          [
            314,
            76
          ],
          [
            317,
            73
          ],
          [
            317,
            69
          ],
          [
            314,
            67
          ],
          [
            314,
            69
          ],
          [
            316,
            71
          ],
          [
            313,
            75
          ],
          [
            308,
            74
          ],
          [
            305,
            71
          ],
          [
            307,
            69
          ]
        ],
        "tile": null,
        "color": [
          255,
          255,
          255,
          20
        ]
      },
      {
        "type": "rect",
        "data": [
          310,
          68,
          1,
          6
        ],
        "tile": null,
        "color": [
          255,
          255,
          255,
          20
        ]
      },
      {
        "type": "rect",
        "data": [
          312,
          71,
          2,
          1
        ],
        "tile": null,
        "color": [
          255,
          255,
          255,
          20
        ]
      },
      {
        "type": "rect",
        "data": [
          307,
          70,
          2,
          1
        ],
        "tile": null,
        "color": [
          255,
          255,
          255,
          20
        ]
      },
      {
        "type": "rect",
        "data": [
          318,
          71,
          1,
          1
        ],
        "tile": null,
        "color": [
          255,
          255,
          255,
          20
        ]
      },
      {
        "type": "rect",
        "data": [
          310,
          65,
          1,
          1
        ],
        "tile": null,
        "color": [
          255,
          255,
          255,
          20
        ]
      },
      {
        "type": "rect",
        "data": [
          310,
          76,
          1,
          1
        ],
        "tile": null,
        "color": [
          255,
          255,
          255,
          20
        ]
      },
      {
        "type": "rect",
        "data": [
          302,
          70,
          1,
          1
        ],
        "tile": null,
        "color": [
          255,
          255,
          255,
          20
        ]
      },
      {
        "type": "rect",
        "data": [
          608,
          -6,
          48,
          375
        ],
        "tile": null,
        "color": [
          25,
          20,
          12
        ]
      },
      {
        "type": "rect",
        "data": [
          71,
          0,
          537,
          14
        ],
        "tile": "wall-blue.png",
        "color": [
          255,
          255,
          255,
          255
        ]
      },
      {
        "type": "rect",
        "data": [
          70,
          12,
          538,
          2
        ],
        "tile": null,
        "color": [
          83,
          57,
          23
        ]
      },
      {
        "type": "rect",
        "data": [
          560,
          0,
          1,
          1
        ],
        "tile": null,
        "color": [
          255,
          255,
          255,
          255
        ]
      }
    ]
  },
  "shadow_zones": [],
  "startups": {
    "unassigned": [
      [
        356,
        56
      ],
      [
        356,
        84
      ],
      [
        356,
        104
      ],
      [
        356,
        123
      ]
    ],
    "groups": [
      {
        "popspots": {
          "left": [
            253,
            260
          ],
          "right": [
            340,
            261
          ],
          "up": [
            298,
            225
          ],
          "down": [
            297,
            294
          ]
        },
        "assigned": [
          [
            263,
            282
          ],
          [
            230,
            282
          ],
          [
            264,
            300
          ],
          [
            231,
            300
          ]
        ],
        "interactions": {
          "left": "startup-1-left",
          "right": "startup-1-right",
          "up": "startup-1-up",
          "down": "startup-1-down"
        }
      },
      {
        "popspots": {
          "left": [
            255,
            159
          ],
          "right": [
            339,
            160
          ],
          "up": [
            296,
            128
          ],
          "down": [
            298,
            201
          ]
        },
        "assigned": [
          [
            265,
            132
          ],
          [
            238,
            132
          ],
          [
            265,
            118
          ],
          [
            239,
            118
          ]
        ],
        "interactions": {
          "left": "startup-2-left",
          "right": "startup-2-right",
          "up": "startup-2-up",
          "down": "startup-2-down"
        }
      },
      {
        "popspots": {
          "left": [
            380,
            160
          ],
          "right": [
            464,
            160
          ],
          "up": [
            421,
            126
          ],
          "down": [
            423,
            194
          ]
        },
        "assigned": [
          [
            462,
            131
          ],
          [
            491,
            131
          ],
          [
            463,
            116
          ],
          [
            489,
            116
          ]
        ],
        "interactions": {
          "left": "startup-3-left",
          "right": "startup-3-right",
          "up": "startup-3-up",
          "down": "startup-3-down"
        }
      },
      {
        "popspots": {
          "left": [
            378,
            261
          ],
          "right": [
            465,
            259
          ],
          "up": [
            421,
            230
          ],
          "down": [
            423,
            297
          ]
        },
        "assigned": [
          [
            458,
            287
          ],
          [
            490,
            287
          ],
          [
            459,
            302
          ],
          [
            490,
            302
          ]
        ],
        "interactions": {
          "left": "startup-4-left",
          "right": "startup-4-right",
          "up": "startup-4-up",
          "down": "startup-4-down"
        }
      }
    ]
  },
  "score": {
    "ol": {
      "file": "resources/sets/street/OL-score.png",
      "position": [
        -30.349733911679373,
        391.0831982471594
      ]
    },
    "player1": {
      "life": {
        "position": [
          16.643034237927985,
          221.23228255076393
        ],
        "file4": "/resources/ui/saloon/player-1/player-1-00.png",
        "file3": "/resources/ui/saloon/player-1/player-1-01.png",
        "file2": "/resources/ui/saloon/player-1/player-1-02.png",
        "file1": "/resources/ui/saloon/player-1/player-1-03.png"
      },
      "coins_position": [
        22.82564034391305,
        235.24618972433007
      ],
      "bullet": {
        "position": [
          22.82564034391305,
          224.52967247395597
        ],
        "on": "/resources/ui/saloon/bullet.png",
        "off": "/resources/ui/saloon/bullet_off.png"
      }
    },
    "player2": {
      "life": {
        "position": [
          17.879555459124997,
          252.96966056148727
        ],
        "file4": "/resources/ui/saloon/player-2/player-2-00.png",
        "file3": "/resources/ui/saloon/player-2/player-2-01.png",
        "file2": "/resources/ui/saloon/player-2/player-2-02.png",
        "file1": "/resources/ui/saloon/player-2/player-2-03.png"
      },
      "coins_position": [
        23.237814084312056,
        266.5713939946544
      ],
      "bullet": {
        "position": [
          23.64998782471106,
          255.8548767442803
        ],
        "on": "/resources/ui/saloon/bullet.png",
        "off": "/resources/ui/saloon/bullet_off.png"
      }
    },
    "player3": {
      "life": {
        "position": [
          24.886509045908074,
          283.8826910914126
        ],
        "file4": "/resources/ui/saloon/player-3/player-3-00.png",
        "file3": "/resources/ui/saloon/player-3/player-3-01.png",
        "file2": "/resources/ui/saloon/player-3/player-3-02.png",
        "file1": "/resources/ui/saloon/player-3/player-3-03.png"
      },
      "coins_position": [
        23.237814084312056,
        299.54529322657476
      ],
      "bullet": {
        "position": [
          22.413466603514046,
          288.41660223580163
        ],
        "on": "/resources/ui/saloon/bullet.png",
        "off": "/resources/ui/saloon/bullet_off.png"
      }
    },
    "player4": {
      "life": {
        "position": [
          23.64998782471106,
          313.9713741405399
        ],
        "file4": "/resources/ui/saloon/player-4/player-4-00.png",
        "file3": "/resources/ui/saloon/player-4/player-4-01.png",
        "file2": "/resources/ui/saloon/player-4/player-4-02.png",
        "file1": "/resources/ui/saloon/player-4/player-4-03.png"
      },
      "coins_position": [
        22.82564034391305,
        327.5731075737071
      ],
      "bullet": {
        "position": [
          22.82564034391305,
          316.44441658293397
        ],
        "on": "/resources/ui/saloon/bullet.png",
        "off": "/resources/ui/saloon/bullet_off.png"
      }
    }
  },
  "fences": [
    [
      137,
      56,
      3,
      280
    ],
    [
      137,
      334,
      403,
      3
    ],
    [
      535,
      61,
      5,
      276
    ],
    [
      137,
      57,
      403,
      4
    ]
  ],
  "no_go_zones": [
    [
      140,
      53,
      400,
      29
    ],
    [
      536,
      53,
      5,
      283
    ],
    [
      137,
      333,
      403,
      4
    ],
    [
      137,
      52,
      4,
      285
    ],
    [
      70,
      0,
      538,
      14
    ],
    [
      0,
      1,
      70,
      359
    ],
    [
      -1,
      360,
      643,
      10
    ],
    [
      608,
      -1,
      35,
      371
    ],
    [
      141,
      82,
      50,
      128
    ]
  ],
  "walls": [
    [
      [
        190,
        211
      ],
      [
        208,
        193
      ],
      [
        207,
        80
      ],
      [
        173,
        79
      ]
    ]
  ],
  "interactions": [
    {
      "gametypes": [
        "basic",
        "advanced"
      ],
      "play_once": true,
      "action": "poker",
      "id": "startup-2-left",
      "busy": true,
      "lockable": true,
      "direction": "right",
      "insound": null,
      "outsound": null,
      "zone": [
        243,
        146,
        25,
        25
      ],
      "target": [
        255,
        159
      ],
      "attraction": [
        238,
        140,
        23,
        40
      ],
      "position": [
        28,
        45
      ]
    },
    {
      "gametypes": [
        "basic",
        "advanced"
      ],
      "play_once": true,
      "action": "poker",
      "id": "startup-2-up",
      "busy": true,
      "lockable": true,
      "direction": "down",
      "insound": null,
      "outsound": null,
      "zone": [
        283,
        118,
        25,
        25
      ],
      "target": [
        295,
        130
      ],
      "attraction": [
        275,
        118,
        46,
        16
      ],
      "position": [
        52,
        22
      ]
    },
    {
      "gametypes": [
        "basic",
        "advanced"
      ],
      "play_once": true,
      "action": "poker",
      "id": "startup-2-right",
      "busy": true,
      "lockable": true,
      "direction": "left",
      "insound": null,
      "outsound": null,
      "zone": [
        328,
        146,
        25,
        25
      ],
      "target": [
        340,
        159
      ],
      "attraction": [
        328,
        142,
        39,
        32
      ],
      "position": [
        78,
        43
      ]
    },
    {
      "gametypes": [
        "basic",
        "advanced"
      ],
      "play_once": true,
      "action": "poker",
      "id": "startup-2-down",
      "busy": true,
      "lockable": true,
      "direction": "up",
      "insound": null,
      "outsound": null,
      "zone": [
        286,
        190,
        25,
        25
      ],
      "target": [
        298,
        201
      ],
      "attraction": [
        282,
        192,
        37,
        30
      ],
      "position": [
        52,
        70
      ]
    },
    {
      "gametypes": [
        "basic",
        "advanced"
      ],
      "play_once": true,
      "action": "poker",
      "id": "startup-1-up",
      "busy": true,
      "lockable": true,
      "direction": "down",
      "insound": null,
      "outsound": null,
      "zone": [
        286,
        212,
        25,
        25
      ],
      "target": [
        298,
        225
      ],
      "attraction": [
        278,
        204,
        42,
        24
      ],
      "position": [
        55,
        289
      ]
    },
    {
      "gametypes": [
        "basic",
        "advanced"
      ],
      "play_once": true,
      "action": "poker",
      "id": "startup-1-right",
      "busy": true,
      "lockable": true,
      "direction": "left",
      "insound": null,
      "outsound": null,
      "zone": [
        327,
        247,
        25,
        25
      ],
      "target": [
        339,
        260
      ],
      "attraction": [
        336,
        243,
        29,
        33
      ],
      "position": [
        82,
        313
      ]
    },
    {
      "gametypes": [
        "basic",
        "advanced"
      ],
      "play_once": true,
      "action": "poker",
      "id": "startup-1-left",
      "busy": true,
      "lockable": true,
      "direction": "right",
      "insound": null,
      "outsound": null,
      "zone": [
        240,
        248,
        25,
        25
      ],
      "target": [
        253,
        261
      ],
      "attraction": [
        232,
        242,
        35,
        39
      ],
      "position": [
        32,
        314
      ]
    },
    {
      "gametypes": [
        "basic",
        "advanced"
      ],
      "play_once": false,
      "action": "poker",
      "id": "startup-1-down",
      "busy": true,
      "lockable": true,
      "direction": "up",
      "insound": null,
      "outsound": null,
      "zone": [
        285,
        280,
        25,
        25
      ],
      "target": [
        297,
        294
      ],
      "attraction": [
        280,
        294,
        38,
        20
      ],
      "position": [
        54,
        336
      ]
    },
    {
      "gametypes": [
        "basic",
        "advanced"
      ],
      "play_once": true,
      "action": "poker",
      "id": "startup-3-up",
      "busy": true,
      "lockable": true,
      "direction": "down",
      "insound": null,
      "outsound": null,
      "zone": [
        409,
        113,
        25,
        25
      ],
      "target": [
        421,
        127
      ],
      "attraction": [
        404,
        101,
        35,
        35
      ],
      "position": [
        559,
        25
      ]
    },
    {
      "gametypes": [
        "basic",
        "advanced"
      ],
      "play_once": true,
      "action": "poker",
      "id": "startup-3-right",
      "busy": true,
      "lockable": true,
      "direction": "left",
      "insound": null,
      "outsound": null,
      "zone": [
        453,
        147,
        25,
        25
      ],
      "target": [
        464,
        160
      ],
      "attraction": [
        463,
        144,
        35,
        35
      ],
      "position": [
        598,
        50
      ]
    },
    {
      "gametypes": [
        "basic",
        "advanced"
      ],
      "play_once": false,
      "action": "poker",
      "id": "startup-3-down",
      "busy": true,
      "lockable": true,
      "direction": "up",
      "insound": null,
      "outsound": null,
      "zone": [
        411,
        182,
        25,
        25
      ],
      "target": [
        423,
        194
      ],
      "attraction": [
        407,
        187,
        35,
        35
      ],
      "position": [
        559,
        72
      ]
    },
    {
      "gametypes": [
        "basic",
        "advanced"
      ],
      "play_once": true,
      "action": "poker",
      "id": "startup-3-left",
      "busy": true,
      "lockable": true,
      "direction": "right",
      "insound": null,
      "outsound": null,
      "zone": [
        366,
        147,
        25,
        25
      ],
      "target": [
        378,
        160
      ],
      "attraction": [
        355,
        142,
        35,
        35
      ],
      "position": [
        512,
        44
      ]
    },
    {
      "gametypes": [
        "basic",
        "advanced"
      ],
      "play_once": true,
      "action": "poker",
      "id": "startup-4-up",
      "busy": true,
      "lockable": true,
      "direction": "down",
      "insound": null,
      "outsound": null,
      "zone": [
        409,
        217,
        25,
        25
      ],
      "target": [
        421,
        230
      ],
      "attraction": [
        396,
        206,
        51,
        26
      ],
      "position": [
        564,
        294
      ]
    },
    {
      "gametypes": [
        "basic",
        "advanced"
      ],
      "play_once": true,
      "action": "poker",
      "id": "startup-4-right",
      "busy": true,
      "lockable": true,
      "direction": "left",
      "insound": null,
      "outsound": null,
      "zone": [
        452,
        245,
        23,
        25
      ],
      "target": [
        464,
        258
      ],
      "attraction": [
        462,
        238,
        22,
        37
      ],
      "position": [
        602,
        310
      ]
    },
    {
      "gametypes": [
        "basic",
        "advanced"
      ],
      "play_once": true,
      "action": "poker",
      "id": "startup-4-down",
      "busy": true,
      "lockable": true,
      "direction": "up",
      "insound": null,
      "outsound": null,
      "zone": [
        411,
        283,
        25,
        25
      ],
      "target": [
        423,
        296
      ],
      "attraction": [
        399,
        289,
        50,
        26
      ],
      "position": [
        564,
        326
      ]
    },
    {
      "gametypes": [
        "basic",
        "advanced"
      ],
      "play_once": true,
      "action": "poker",
      "id": "startup-4-left",
      "busy": true,
      "lockable": true,
      "direction": "right",
      "insound": null,
      "outsound": null,
      "zone": [
        365,
        246,
        25,
        26
      ],
      "target": [
        378,
        260
      ],
      "attraction": [
        352,
        243,
        35,
        34
      ],
      "position": [
        517,
        306
      ]
    }
  ],
  "popspots": [
    {
      "gametypes": [
        "basic",
        "advanced"
      ],
      "position": [
        94,
        30
      ]
    },
    {
      "gametypes": [
        "basic",
        "advanced"
      ],
      "position": [
        103,
        47
      ]
    },
    {
      "gametypes": [
        "basic",
        "advanced"
      ],
      "position": [
        110,
        76
      ]
    },
    {
      "gametypes": [
        "basic",
        "advanced"
      ],
      "position": [
        92,
        104
      ]
    },
    {
      "gametypes": [
        "basic",
        "advanced"
      ],
      "position": [
        118,
        131
      ]
    },
    {
      "gametypes": [
        "basic",
        "advanced"
      ],
      "position": [
        103,
        153
      ]
    },
    {
      "gametypes": [
        "basic",
        "advanced"
      ],
      "position": [
        95,
        186
      ]
    },
    {
      "gametypes": [
        "basic",
        "advanced"
      ],
      "position": [
        108,
        205
      ]
    },
    {
      "gametypes": [
        "basic",
        "advanced"
      ],
      "position": [
        118,
        210
      ]
    },
    {
      "gametypes": [
        "basic",
        "advanced"
      ],
      "position": [
        118,
        245
      ]
    },
    {
      "gametypes": [
        "basic",
        "advanced"
      ],
      "position": [
        98,
        258
      ]
    },
    {
      "gametypes": [
        "basic",
        "advanced"
      ],
      "position": [
        83,
        282
      ]
    },
    {
      "gametypes": [
        "basic",
        "advanced"
      ],
      "position": [
        101,
        308
      ]
    },
    {
      "gametypes": [
        "basic",
        "advanced"
      ],
      "position": [
        113,
        325
      ]
    },
    {
      "gametypes": [
        "basic",
        "advanced"
      ],
      "position": [
        97,
        344
      ]
    },
    {
      "gametypes": [
        "basic",
        "advanced"
      ],
      "position": [
        118,
        283
      ]
    },
    {
      "gametypes": [
        "basic",
        "advanced"
      ],
      "position": [
        140,
        353
      ]
    },
    {
      "gametypes": [
        "basic",
        "advanced"
      ],
      "position": [
        184,
        350
      ]
    },
    {
      "gametypes": [
        "basic",
        "advanced"
      ],
      "position": [
        239,
        351
      ]
    },
    {
      "gametypes": [
        "basic",
        "advanced"
      ],
      "position": [
        272,
        352
      ]
    },
    {
      "gametypes": [
        "basic",
        "advanced"
      ],
      "position": [
        341,
        351
      ]
    },
    {
      "gametypes": [
        "basic",
        "advanced"
      ],
      "position": [
        383,
        351
      ]
    },
    {
      "gametypes": [
        "basic",
        "advanced"
      ],
      "position": [
        443,
        351
      ]
    },
    {
      "gametypes": [
        "basic",
        "advanced"
      ],
      "position": [
        474,
        348
      ]
    },
    {
      "gametypes": [
        "basic",
        "advanced"
      ],
      "position": [
        518,
        346
      ]
    },
    {
      "gametypes": [
        "basic",
        "advanced"
      ],
      "position": [
        553,
        346
      ]
    },
    {
      "gametypes": [
        "basic",
        "advanced"
      ],
      "position": [
        578,
        336
      ]
    },
    {
      "gametypes": [
        "basic",
        "advanced"
      ],
      "position": [
        572,
        310
      ]
    },
    {
      "gametypes": [
        "basic",
        "advanced"
      ],
      "position": [
        554,
        283
      ]
    },
    {
      "gametypes": [
        "basic",
        "advanced"
      ],
      "position": [
        588,
        267
      ]
    },
    {
      "gametypes": [
        "basic",
        "advanced"
      ],
      "position": [
        573,
        226
      ]
    },
    {
      "gametypes": [
        "basic",
        "advanced"
      ],
      "position": [
        564,
        197
      ]
    },
    {
      "gametypes": [
        "basic",
        "advanced"
      ],
      "position": [
        588,
        181
      ]
    },
    {
      "gametypes": [
        "basic",
        "advanced"
      ],
      "position": [
        578,
        142
      ]
    },
    {
      "gametypes": [
        "basic",
        "advanced"
      ],
      "position": [
        562,
        117
      ]
    },
    {
      "gametypes": [
        "basic",
        "advanced"
      ],
      "position": [
        579,
        97
      ]
    },
    {
      "gametypes": [
        "basic",
        "advanced"
      ],
      "position": [
        587,
        74
      ]
    },
    {
      "gametypes": [
        "basic",
        "advanced"
      ],
      "position": [
        587,
        49
      ]
    },
    {
      "gametypes": [
        "basic",
        "advanced"
      ],
      "position": [
        565,
        36
      ]
    },
    {
      "gametypes": [
        "basic",
        "advanced"
      ],
      "position": [
        503,
        28
      ]
    },
    {
      "gametypes": [
        "basic",
        "advanced"
      ],
      "position": [
        474,
        35
      ]
    },
    {
      "gametypes": [
        "basic",
        "advanced"
      ],
      "position": [
        445,
        26
      ]
    },
    {
      "gametypes": [
        "basic",
        "advanced"
      ],
      "position": [
        422,
        41
      ]
    },
    {
      "gametypes": [
        "basic",
        "advanced"
      ],
      "position": [
        388,
        32
      ]
    },
    {
      "gametypes": [
        "basic",
        "advanced"
      ],
      "position": [
        352,
        27
      ]
    },
    {
      "gametypes": [
        "basic",
        "advanced"
      ],
      "position": [
        318,
        31
      ]
    },
    {
      "gametypes": [
        "basic",
        "advanced"
      ],
      "position": [
        295,
        36
      ]
    },
    {
      "gametypes": [
        "basic",
        "advanced"
      ],
      "position": [
        269,
        29
      ]
    },
    {
      "gametypes": [
        "basic",
        "advanced"
      ],
      "position": [
        243,
        37
      ]
    },
    {
      "gametypes": [
        "basic",
        "advanced"
      ],
      "position": [
        216,
        27
      ]
    },
    {
      "gametypes": [
        "basic",
        "advanced"
      ],
      "position": [
        419,
        24
      ]
    },
    {
      "gametypes": [
        "basic",
        "advanced"
      ],
      "position": [
        596,
        24
      ]
    },
    {
      "gametypes": [
        "basic",
        "advanced"
      ],
      "position": [
        562,
        72
      ]
    }
  ],
  "stairs": [],
  "backgrounds": [
    {
      "file": "/resources/placeholder/No name.png",
      "position": [
        0,
        0
      ]
    }
  ],
  "targets": [
    {
      "gametypes": [
        "basic",
        "advanced"
      ],
      "origin": [
        137,
        336,
        404,
        24
      ],
      "weight": 3,
      "destinations": [
        [
          548,
          338,
          50,
          17
        ],
        [
          77,
          340,
          53,
          15
        ],
        [
          144,
          343,
          389,
          13
        ]
      ]
    },
    {
      "gametypes": [
        "basic",
        "advanced"
      ],
      "origin": [
        70,
        59,
        67,
        276
      ],
      "weight": 3,
      "destinations": [
        [
          77,
          339,
          53,
          16
        ]
      ]
    },
    {
      "gametypes": [
        "basic",
        "advanced"
      ],
      "origin": [
        81,
        67,
        44,
        257
      ],
      "weight": 3,
      "destinations": [
        [
          87,
          22,
          34,
          29
        ]
      ]
    },
    {
      "gametypes": [
        "basic",
        "advanced"
      ],
      "origin": [
        70,
        12,
        66,
        47
      ],
      "weight": 3,
      "destinations": [
        [
          83,
          20,
          40,
          331
        ],
        [
          77,
          338,
          53,
          17
        ],
        [
          83,
          20,
          517,
          27
        ],
        [
          548,
          19,
          53,
          29
        ]
      ]
    },
    {
      "gametypes": [
        "basic",
        "advanced"
      ],
      "origin": [
        137,
        11,
        409,
        45
      ],
      "weight": 3,
      "destinations": [
        [
          82,
          19,
          42,
          32
        ],
        [
          82,
          19,
          519,
          29
        ],
        [
          548,
          20,
          55,
          29
        ]
      ]
    },
    {
      "gametypes": [
        "basic",
        "advanced"
      ],
      "origin": [
        538,
        11,
        71,
        49
      ],
      "weight": 3,
      "destinations": [
        [
          82,
          19,
          455,
          29
        ],
        [
          83,
          22,
          40,
          29
        ],
        [
          548,
          22,
          51,
          333
        ],
        [
          548,
          337,
          51,
          18
        ]
      ]
    },
    {
      "gametypes": [
        "basic",
        "advanced"
      ],
      "origin": [
        538,
        61,
        70,
        275
      ],
      "weight": 3,
      "destinations": [
        [
          548,
          19,
          51,
          336
        ],
        [
          548,
          336,
          51,
          19
        ],
        [
          549,
          19,
          52,
          29
        ]
      ]
    },
    {
      "gametypes": [
        "basic",
        "advanced"
      ],
      "origin": [
        539,
        336,
        69,
        24
      ],
      "weight": 3,
      "destinations": [
        [
          78,
          341,
          523,
          17
        ],
        [
          551,
          18,
          52,
          338
        ],
        [
          548,
          19,
          53,
          31
        ]
      ]
    },
    {
      "gametypes": [
        "basic",
        "advanced"
      ],
      "origin": [
        69,
        334,
        68,
        25
      ],
      "weight": 3,
      "destinations": [
        [
          82,
          19,
          41,
          188
        ],
        [
          340,
          342,
          261,
          14
        ]
      ]
    }
  ],
  "npcs": [
    {
      "type": "sniper",
      "file": "resources/animdata/sniper.json",
      "gametypes": [
        "basic",
        "advanced"
      ],
      "startposition": [
        229,
        -4
      ],
      "y": 400,
      "zone": [
        139,
        71,
        399,
        261
      ],
      "interaction_zone": [
        299,
        66,
        32,
        30
      ]
    },
    {
      "type": "barman",
      "file": "resources/animdata/barman.json",
      "gametypes": [
        "basic",
        "advanced"
      ],
      "startposition": [
        130,
        60
      ],
      "direction": "left",
      "path": [
        [
          130,
          60
        ],
        [
          130,
          90
        ]
      ]
    }
  ],
  "characters": [
    "resources/animdata/smith.json",
    "resources/animdata/kate.json",
    "resources/animdata/janet.json",
    "resources/animdata/jo.json"
  ],
  "overlays": [],
  "vfx": [
    {
      "name": "vomit",
      "type": "static",
      "file": "resources/props/vomit.png",
      "y": -1000
    },
    {
      "name": "coin-alert",
      "type": "animated",
      "file": "resources/vfx/coin-alert.json"
    }
  ],
  "interactive_props": [
    {
      "name": "bottle",
      "action": "drink",
      "insound": "resources/sounds/glouglou.wav",
      "outsound": null,
      "offset": [
        20,
        -20
      ],
      "target": [
        -20,
        20
      ],
      "play_once": false,
      "zone": [
        -40,
        0,
        40,
        30
      ],
      "image": "resources/props/beer.png",
      "switch": 15,
      "attraction": [
        -100,
        -30,
        100,
        100
      ],
      "direction": "right",
      "lockable": false
    }
  ],
  "props": [
    {
      "gametypes": [
        "basic",
        "advanced"
      ],
      "visible_at_dispatch": true,
      "file": "resources/props/poker-droite-bas.png",
      "center": [
        0,
        18
      ],
      "position": [
        390,
        152
      ],
      "box": [
        2,
        0,
        58,
        25
      ]
    },
    {
      "gametypes": [
        "basic",
        "advanced"
      ],
      "visible_at_dispatch": true,
      "file": "resources/props/poker-droite-haut.png",
      "center": [
        0,
        15
      ],
      "position": [
        265,
        152
      ],
      "box": [
        2,
        0,
        58,
        25
      ]
    },
    {
      "gametypes": [
        "basic",
        "advanced"
      ],
      "visible_at_dispatch": true,
      "file": "resources/props/poker-gauche-bas.png",
      "center": [
        0,
        15
      ],
      "position": [
        265,
        253
      ],
      "box": [
        2,
        0,
        58,
        25
      ]
    },
    {
      "gametypes": [
        "basic",
        "advanced"
      ],
      "visible_at_dispatch": true,
      "file": "resources/props/poker-gauche-haut.png",
      "center": [
        0,
        15
      ],
      "position": [
        390,
        253
      ],
      "box": [
        2,
        0,
        58,
        25
      ]
    },
    {
      "gametypes": [
        "basic",
        "advanced"
      ],
      "visible_at_dispatch": true,
      "file": "resources/props/comptoir.png",
      "center": [
        0,
        -12
      ],
      "position": [
        159,
        44
      ],
      "box": [
        0,
        0,
        30,
        136
      ]
    }
  ]
}